kuksa_certificates/CA.key
kuksa_certificates/CA.pem
kuksa_certificates/Client.key
kuksa_certificates/Client.pem
kuksa_certificates/README.md
kuksa_certificates/Server.key
kuksa_certificates/Server.pem
kuksa_certificates/__init__.py
kuksa_certificates/genCerts.sh
kuksa_certificates/jwt.pub.key
kuksa_certificates/jwt/all-read-write.json
kuksa_certificates/jwt/all-read-write.json.token
kuksa_certificates/jwt/createToken.py
kuksa_certificates/jwt/jwt.key
kuksa_certificates/jwt/jwt.key.pub
kuksa_certificates/jwt/recreateJWTkeyPair.sh
kuksa_certificates/jwt/requirements.txt
kuksa_certificates/jwt/single-read.json
kuksa_certificates/jwt/single-read.json.token
kuksa_certificates/jwt/super-admin.json
kuksa_certificates/jwt/super-admin.json.token
kuksa_viss_client/KuksaGrpcComm.py
kuksa_viss_client/KuksaWsComm.py
kuksa_viss_client/LICENSE
kuksa_viss_client/__init__.py
kuksa_viss_client/__main__.py
kuksa_viss_client/_metadata.py
kuksa_viss_client/kuksa_pb2.py
kuksa_viss_client/kuksa_pb2_grpc.py
kuksa_viss_client/logo
kuksa_viss_client-0.2.5.dist-info/LICENSE
kuksa_viss_client-0.2.5.dist-info/METADATA
kuksa_viss_client-0.2.5.dist-info/WHEEL
kuksa_viss_client-0.2.5.dist-info/entry_points.txt
kuksa_viss_client-0.2.5.dist-info/top_level.txt
kuksa_viss_client-0.2.5.dist-info/RECORD
