Metadata-Version: 2.1
Name: kuksa-viss-client
Version: 0.2.5
Summary: kuksa.val python clients and SDK
Home-page: https://github.com/eclipse/kuksa.val
Author: Sebastian Schildt, Naresh Nayak, Wenwen Chen
Author-email: sebastian.schildt@de.bosch.com, naresh.nayak@de.bosch.com, wenwen.chen@de.bosch.com
License: UNKNOWN
Project-URL: Source, https://github.com/eclipse/kuksa.val/tree/master/kuksa_viss_client
Project-URL: Bug Tracker, https://github.com/eclipse/kuksa.val/issues
Platform: UNKNOWN
Classifier: Intended Audience :: Developers
Classifier: Development Status :: 3 - Alpha
Classifier: Environment :: Console
Classifier: Programming Language :: Python :: 3
Classifier: License :: OSI Approved :: Apache Software License
Classifier: Operating System :: OS Independent
Classifier: Topic :: Software Development
Requires-Python: >=3.8
Requires-Dist: cmd2 (~=1.4)
Requires-Dist: grpcio-tools (~=1.46.0)
Requires-Dist: grpcio (~=1.46.0)
Requires-Dist: importlib-metadata (>=3.6)
Requires-Dist: jsonpath-ng (~=1.5.3)
Requires-Dist: pygments (~=2.5)
Requires-Dist: websockets (~=10.1)
